[{"id":1,"rating":4,"vote_count":10},{"id":2,"rating":5,"vote_count":10},{"id":3,"rating":5,"vote_count":4},{"id":4,"rating":5,"vote_count":18},{"id":5,"rating":4,"vote_count":710},{"id":237,"rating":5,"vote_count":67},{"id":6,"rating":4,"vote_count":5},{"id":7,"rating":5,"vote_count":1},{"id":8,"rating":4,"vote_count":81},{"id":9,"rating":5,"vote_count":135},{"id":10,"rating":5,"vote_count":6},{"id":11,"rating":5,"vote_count":38},{"id":12,"rating":3,"vote_count":8},{"id":13,"rating":5,"vote_count":6},{"id":14,"rating":4,"vote_count":5},{"id":15,"rating":4,"vote_count":13},{"id":16,"rating":4,"vote_count":66},{"id":17,"rating":5,"vote_count":15},{"id":18,"rating":5,"vote_count":5},{"id":238,"rating":5,"vote_count":16},{"id":19,"rating":4,"vote_count":16},{"id":20,"rating":4,"vote_count":3},{"id":21,"rating":5,"vote_count":6},{"id":22,"rating":4,"vote_count":3},{"id":23,"rating":5,"vote_count":74},{"id":24,"rating":5,"vote_count":12},{"id":1228,"rating":5,"vote_count":1},{"id":25,"rating":4,"vote_count":14},{"id":26,"rating":4,"vote_count":7},{"id":27,"rating":5,"vote_count":2},{"id":28,"rating":5,"vote_count":2},{"id":29,"rating":5,"vote_count":205},{"id":30,"rating":5,"vote_count":22},{"id":31,"rating":5,"vote_count":2},{"id":32,"rating":4,"vote_count":2},{"id":33,"rating":5,"vote_count":26},{"id":38,"rating":5,"vote_count":24},{"id":34,"rating":4,"vote_count":3},{"id":35,"rating":5,"vote_count":30},{"id":36,"rating":5,"vote_count":28},{"id":37,"rating":5,"vote_count":11},{"id":66,"rating":5,"vote_count":56},{"id":39,"rating":5,"vote_count":5},{"id":40,"rating":4,"vote_count":16},{"id":41,"rating":4,"vote_count":16},{"id":42,"rating":5,"vote_count":58},{"id":43,"rating":5,"vote_count":11},{"id":44,"rating":4,"vote_count":29},{"id":45,"rating":5,"vote_count":71},{"id":46,"rating":5,"vote_count":8},{"id":47,"rating":4,"vote_count":3},{"id":48,"rating":4,"vote_count":11},{"id":49,"rating":3,"vote_count":4},{"id":50,"rating":5,"vote_count":2},{"id":51,"rating":4,"vote_count":37},{"id":52,"rating":5,"vote_count":7},{"id":53,"rating":5,"vote_count":3},{"id":54,"rating":5,"vote_count":1},{"id":239,"rating":4,"vote_count":20},{"id":55,"rating":5,"vote_count":21},{"id":56,"rating":4,"vote_count":144},{"id":57,"rating":5,"vote_count":238},{"id":58,"rating":4,"vote_count":16},{"id":59,"rating":5,"vote_count":166},{"id":60,"rating":4,"vote_count":6},{"id":61,"rating":5,"vote_count":3},{"id":62,"rating":5,"vote_count":39},{"id":63,"rating":5,"vote_count":21},{"id":64,"rating":4,"vote_count":4},{"id":65,"rating":5,"vote_count":32},{"id":67,"rating":4,"vote_count":7},{"id":68,"rating":5,"vote_count":4},{"id":69,"rating":5,"vote_count":36},{"id":70,"rating":4,"vote_count":33},{"id":71,"rating":4,"vote_count":13},{"id":72,"rating":5,"vote_count":5},{"id":73,"rating":5,"vote_count":7},{"id":74,"rating":5,"vote_count":7},{"id":75,"rating":5,"vote_count":30},{"id":76,"rating":4,"vote_count":75},{"id":77,"rating":4,"vote_count":17},{"id":78,"rating":4,"vote_count":16},{"id":79,"rating":3,"vote_count":9},{"id":80,"rating":5,"vote_count":48},{"id":81,"rating":5,"vote_count":32},{"id":82,"rating":4,"vote_count":28},{"id":83,"rating":5,"vote_count":4},{"id":84,"rating":4,"vote_count":68},{"id":85,"rating":4,"vote_count":24},{"id":86,"rating":4,"vote_count":13},{"id":87,"rating":5,"vote_count":161},{"id":88,"rating":4,"vote_count":58},{"id":89,"rating":4,"vote_count":126},{"id":90,"rating":4,"vote_count":374},{"id":91,"rating":5,"vote_count":2531},{"id":92,"rating":5,"vote_count":62},{"id":93,"rating":5,"vote_count":12},{"id":125,"rating":5,"vote_count":9},{"id":94,"rating":4,"vote_count":2},{"id":95,"rating":5,"vote_count":30},{"id":96,"rating":4,"vote_count":16},{"id":97,"rating":4,"vote_count":60},{"id":126,"rating":4,"vote_count":19},{"id":98,"rating":5,"vote_count":9},{"id":99,"rating":5,"vote_count":42},{"id":100,"rating":4,"vote_count":43},{"id":101,"rating":5,"vote_count":2494},{"id":102,"rating":5,"vote_count":22},{"id":244,"rating":5,"vote_count":13},{"id":103,"rating":5,"vote_count":60},{"id":104,"rating":5,"vote_count":88},{"id":105,"rating":5,"vote_count":79},{"id":106,"rating":4,"vote_count":7},{"id":107,"rating":4,"vote_count":17},{"id":108,"rating":5,"vote_count":10},{"id":109,"rating":5,"vote_count":648},{"id":110,"rating":4,"vote_count":9},{"id":111,"rating":5,"vote_count":12},{"id":112,"rating":5,"vote_count":62},{"id":253,"rating":5,"vote_count":13},{"id":113,"rating":4,"vote_count":27},{"id":114,"rating":5,"vote_count":54},{"id":115,"rating":5,"vote_count":69},{"id":116,"rating":4,"vote_count":25},{"id":117,"rating":5,"vote_count":18},{"id":118,"rating":5,"vote_count":13},{"id":254,"rating":5,"vote_count":20},{"id":119,"rating":4,"vote_count":42},{"id":120,"rating":5,"vote_count":290},{"id":121,"rating":5,"vote_count":317},{"id":122,"rating":5,"vote_count":22},{"id":123,"rating":4,"vote_count":112},{"id":124,"rating":4,"vote_count":10},{"id":127,"rating":4,"vote_count":224},{"id":128,"rating":5,"vote_count":14},{"id":129,"rating":5,"vote_count":22},{"id":130,"rating":4,"vote_count":289},{"id":131,"rating":4,"vote_count":1},{"id":132,"rating":5,"vote_count":3},{"id":240,"rating":4,"vote_count":17},{"id":133,"rating":5,"vote_count":1},{"id":134,"rating":5,"vote_count":79},{"id":135,"rating":5,"vote_count":68},{"id":136,"rating":5,"vote_count":10},{"id":137,"rating":4,"vote_count":4},{"id":148,"rating":5,"vote_count":250},{"id":138,"rating":5,"vote_count":198},{"id":139,"rating":4,"vote_count":141},{"id":140,"rating":5,"vote_count":143},{"id":141,"rating":5,"vote_count":23},{"id":142,"rating":5,"vote_count":707},{"id":159,"rating":4,"vote_count":290},{"id":143,"rating":5,"vote_count":80},{"id":144,"rating":5,"vote_count":581},{"id":145,"rating":5,"vote_count":259},{"id":146,"rating":5,"vote_count":132},{"id":147,"rating":5,"vote_count":223},{"id":241,"rating":5,"vote_count":91},{"id":149,"rating":4,"vote_count":14},{"id":150,"rating":5,"vote_count":368},{"id":151,"rating":4,"vote_count":110},{"id":152,"rating":5,"vote_count":907},{"id":153,"rating":5,"vote_count":628},{"id":160,"rating":5,"vote_count":170},{"id":154,"rating":4,"vote_count":19},{"id":155,"rating":5,"vote_count":318},{"id":156,"rating":4,"vote_count":126},{"id":157,"rating":5,"vote_count":194},{"id":158,"rating":4,"vote_count":249},{"id":161,"rating":4,"vote_count":65},{"id":162,"rating":5,"vote_count":59},{"id":163,"rating":4,"vote_count":92},{"id":164,"rating":5,"vote_count":6},{"id":165,"rating":5,"vote_count":36},{"id":242,"rating":5,"vote_count":17},{"id":166,"rating":4,"vote_count":17},{"id":167,"rating":5,"vote_count":12},{"id":168,"rating":4,"vote_count":58},{"id":169,"rating":5,"vote_count":73},{"id":170,"rating":5,"vote_count":139},{"id":202,"rating":5,"vote_count":2},{"id":171,"rating":4,"vote_count":161},{"id":172,"rating":4,"vote_count":102},{"id":173,"rating":5,"vote_count":123},{"id":174,"rating":5,"vote_count":118},{"id":175,"rating":5,"vote_count":54},{"id":176,"rating":5,"vote_count":18},{"id":177,"rating":4,"vote_count":9},{"id":178,"rating":5,"vote_count":124},{"id":179,"rating":4,"vote_count":99},{"id":180,"rating":5,"vote_count":92},{"id":181,"rating":5,"vote_count":233},{"id":208,"rating":5,"vote_count":10},{"id":182,"rating":4,"vote_count":36},{"id":183,"rating":4,"vote_count":43},{"id":184,"rating":5,"vote_count":25},{"id":185,"rating":4,"vote_count":293},{"id":186,"rating":4,"vote_count":124},{"id":243,"rating":5,"vote_count":20},{"id":187,"rating":4,"vote_count":59},{"id":188,"rating":5,"vote_count":91},{"id":189,"rating":5,"vote_count":177},{"id":190,"rating":5,"vote_count":278},{"id":191,"rating":4,"vote_count":62},{"id":192,"rating":5,"vote_count":257},{"id":193,"rating":5,"vote_count":44},{"id":194,"rating":4,"vote_count":30},{"id":195,"rating":4,"vote_count":36},{"id":196,"rating":4,"vote_count":19},{"id":227,"rating":5,"vote_count":3},{"id":197,"rating":4,"vote_count":10},{"id":198,"rating":5,"vote_count":66},{"id":199,"rating":5,"vote_count":45},{"id":200,"rating":4,"vote_count":97},{"id":201,"rating":4,"vote_count":23},{"id":236,"rating":4,"vote_count":7},{"id":203,"rating":5,"vote_count":115},{"id":204,"rating":4,"vote_count":3},{"id":205,"rating":5,"vote_count":90},{"id":206,"rating":4,"vote_count":4},{"id":207,"rating":5,"vote_count":10},{"id":209,"rating":5,"vote_count":14},{"id":210,"rating":4,"vote_count":10},{"id":211,"rating":4,"vote_count":585},{"id":212,"rating":4,"vote_count":10},{"id":213,"rating":4,"vote_count":8},{"id":214,"rating":4,"vote_count":46},{"id":215,"rating":4,"vote_count":60},{"id":216,"rating":5,"vote_count":2},{"id":217,"rating":5,"vote_count":297},{"id":218,"rating":5,"vote_count":59},{"id":219,"rating":5,"vote_count":46},{"id":220,"rating":3,"vote_count":40},{"id":221,"rating":4,"vote_count":56},{"id":222,"rating":5,"vote_count":10},{"id":223,"rating":4,"vote_count":50},{"id":224,"rating":3,"vote_count":2},{"id":225,"rating":5,"vote_count":1},{"id":226,"rating":5,"vote_count":32},{"id":228,"rating":5,"vote_count":7},{"id":229,"rating":4,"vote_count":17},{"id":230,"rating":4,"vote_count":17},{"id":231,"rating":5,"vote_count":22},{"id":232,"rating":4,"vote_count":4},{"id":233,"rating":4,"vote_count":7},{"id":234,"rating":5,"vote_count":13},{"id":235,"rating":4,"vote_count":3},{"id":245,"rating":4,"vote_count":10},{"id":246,"rating":5,"vote_count":13},{"id":247,"rating":4,"vote_count":4},{"id":248,"rating":5,"vote_count":4},{"id":249,"rating":5,"vote_count":22},{"id":250,"rating":5,"vote_count":3},{"id":251,"rating":5,"vote_count":12},{"id":252,"rating":5,"vote_count":40},{"id":255,"rating":4,"vote_count":6},{"id":256,"rating":5,"vote_count":159},{"id":257,"rating":5,"vote_count":14},{"id":258,"rating":4,"vote_count":3},{"id":259,"rating":5,"vote_count":6},{"id":260,"rating":4,"vote_count":3},{"id":261,"rating":5,"vote_count":59},{"id":262,"rating":5,"vote_count":100},{"id":263,"rating":5,"vote_count":15},{"id":264,"rating":5,"vote_count":12},{"id":457,"rating":5,"vote_count":6},{"id":265,"rating":5,"vote_count":158},{"id":266,"rating":5,"vote_count":44},{"id":267,"rating":4,"vote_count":25},{"id":268,"rating":4,"vote_count":10},{"id":269,"rating":4,"vote_count":32},{"id":270,"rating":5,"vote_count":24},{"id":271,"rating":5,"vote_count":13},{"id":272,"rating":5,"vote_count":1},{"id":273,"rating":4,"vote_count":6},{"id":274,"rating":4,"vote_count":3},{"id":333,"rating":5,"vote_count":5},{"id":275,"rating":4,"vote_count":9},{"id":276,"rating":5,"vote_count":8},{"id":277,"rating":4,"vote_count":4},{"id":278,"rating":5,"vote_count":2},{"id":279,"rating":5,"vote_count":18},{"id":280,"rating":5,"vote_count":32},{"id":281,"rating":5,"vote_count":15},{"id":282,"rating":5,"vote_count":27},{"id":283,"rating":5,"vote_count":1},{"id":284,"rating":4,"vote_count":30},{"id":285,"rating":4,"vote_count":10},{"id":286,"rating":4,"vote_count":13},{"id":287,"rating":4,"vote_count":5},{"id":288,"rating":5,"vote_count":6},{"id":289,"rating":4,"vote_count":3},{"id":290,"rating":5,"vote_count":4},{"id":301,"rating":5,"vote_count":30},{"id":291,"rating":4,"vote_count":120},{"id":292,"rating":5,"vote_count":5},{"id":293,"rating":4,"vote_count":91},{"id":294,"rating":5,"vote_count":120},{"id":295,"rating":4,"vote_count":70},{"id":296,"rating":5,"vote_count":80},{"id":297,"rating":5,"vote_count":40},{"id":298,"rating":5,"vote_count":38},{"id":299,"rating":5,"vote_count":33},{"id":300,"rating":5,"vote_count":232},{"id":302,"rating":4,"vote_count":45},{"id":303,"rating":4,"vote_count":41},{"id":304,"rating":5,"vote_count":21},{"id":305,"rating":5,"vote_count":39},{"id":306,"rating":5,"vote_count":30},{"id":307,"rating":4,"vote_count":24},{"id":308,"rating":5,"vote_count":22},{"id":309,"rating":4,"vote_count":1},{"id":310,"rating":4,"vote_count":10},{"id":311,"rating":5,"vote_count":29},{"id":312,"rating":5,"vote_count":5},{"id":313,"rating":4,"vote_count":3},{"id":314,"rating":5,"vote_count":3},{"id":315,"rating":4,"vote_count":6},{"id":316,"rating":5,"vote_count":4},{"id":317,"rating":5,"vote_count":8},{"id":318,"rating":3,"vote_count":5},{"id":319,"rating":5,"vote_count":1},{"id":320,"rating":5,"vote_count":6},{"id":321,"rating":5,"vote_count":1},{"id":322,"rating":4,"vote_count":6},{"id":323,"rating":5,"vote_count":5},{"id":324,"rating":5,"vote_count":21},{"id":325,"rating":5,"vote_count":7},{"id":326,"rating":4,"vote_count":4},{"id":327,"rating":4,"vote_count":2},{"id":328,"rating":5,"vote_count":7},{"id":329,"rating":4,"vote_count":5},{"id":330,"rating":4,"vote_count":5},{"id":331,"rating":5,"vote_count":26},{"id":332,"rating":5,"vote_count":10},{"id":1229,"rating":4,"vote_count":1},{"id":334,"rating":4,"vote_count":3},{"id":335,"rating":5,"vote_count":29},{"id":336,"rating":5,"vote_count":15},{"id":337,"rating":5,"vote_count":8},{"id":353,"rating":5,"vote_count":5},{"id":338,"rating":5,"vote_count":44},{"id":339,"rating":5,"vote_count":7},{"id":340,"rating":5,"vote_count":18},{"id":341,"rating":5,"vote_count":10},{"id":342,"rating":5,"vote_count":12},{"id":343,"rating":5,"vote_count":277},{"id":344,"rating":5,"vote_count":19},{"id":345,"rating":4,"vote_count":18},{"id":346,"rating":5,"vote_count":31},{"id":347,"rating":5,"vote_count":16},{"id":348,"rating":5,"vote_count":72},{"id":349,"rating":5,"vote_count":7},{"id":350,"rating":5,"vote_count":82},{"id":351,"rating":5,"vote_count":23},{"id":352,"rating":4,"vote_count":193},{"id":354,"rating":5,"vote_count":72},{"id":355,"rating":4,"vote_count":50},{"id":356,"rating":5,"vote_count":14},{"id":357,"rating":5,"vote_count":13},{"id":358,"rating":4,"vote_count":6},{"id":364,"rating":5,"vote_count":2},{"id":359,"rating":5,"vote_count":39},{"id":360,"rating":5,"vote_count":11},{"id":361,"rating":4,"vote_count":10},{"id":362,"rating":5,"vote_count":122},{"id":363,"rating":5,"vote_count":2},{"id":365,"rating":4,"vote_count":37},{"id":366,"rating":5,"vote_count":37},{"id":367,"rating":5,"vote_count":6},{"id":368,"rating":4,"vote_count":7},{"id":369,"rating":5,"vote_count":6},{"id":422,"rating":5,"vote_count":3},{"id":370,"rating":3,"vote_count":2},{"id":371,"rating":5,"vote_count":13},{"id":372,"rating":4,"vote_count":5},{"id":373,"rating":5,"vote_count":5},{"id":374,"rating":5,"vote_count":2},{"id":379,"rating":5,"vote_count":46},{"id":375,"rating":4,"vote_count":6},{"id":376,"rating":5,"vote_count":17},{"id":377,"rating":5,"vote_count":2},{"id":378,"rating":5,"vote_count":19},{"id":414,"rating":4,"vote_count":6},{"id":380,"rating":5,"vote_count":25},{"id":381,"rating":5,"vote_count":308},{"id":382,"rating":5,"vote_count":24},{"id":383,"rating":5,"vote_count":12},{"id":384,"rating":5,"vote_count":154},{"id":385,"rating":5,"vote_count":30},{"id":386,"rating":5,"vote_count":9},{"id":387,"rating":4,"vote_count":5},{"id":388,"rating":5,"vote_count":21},{"id":389,"rating":5,"vote_count":176},{"id":390,"rating":4,"vote_count":3},{"id":391,"rating":5,"vote_count":31},{"id":392,"rating":4,"vote_count":28},{"id":393,"rating":5,"vote_count":25},{"id":394,"rating":4,"vote_count":49},{"id":395,"rating":5,"vote_count":13},{"id":430,"rating":4,"vote_count":4},{"id":396,"rating":4,"vote_count":12},{"id":397,"rating":5,"vote_count":24},{"id":398,"rating":5,"vote_count":8},{"id":399,"rating":5,"vote_count":18},{"id":400,"rating":5,"vote_count":3},{"id":401,"rating":4,"vote_count":17},{"id":402,"rating":5,"vote_count":14},{"id":403,"rating":4,"vote_count":12},{"id":404,"rating":5,"vote_count":3},{"id":405,"rating":5,"vote_count":7},{"id":406,"rating":5,"vote_count":2},{"id":407,"rating":5,"vote_count":1},{"id":415,"rating":5,"vote_count":4},{"id":408,"rating":5,"vote_count":57},{"id":409,"rating":5,"vote_count":54},{"id":410,"rating":5,"vote_count":12},{"id":411,"rating":5,"vote_count":14},{"id":412,"rating":5,"vote_count":2},{"id":413,"rating":5,"vote_count":38},{"id":416,"rating":3,"vote_count":3},{"id":417,"rating":4,"vote_count":407},{"id":418,"rating":4,"vote_count":134},{"id":419,"rating":5,"vote_count":9},{"id":420,"rating":5,"vote_count":9},{"id":421,"rating":1,"vote_count":2},{"id":423,"rating":4,"vote_count":36},{"id":424,"rating":5,"vote_count":2},{"id":425,"rating":4,"vote_count":5},{"id":426,"rating":3,"vote_count":2},{"id":427,"rating":5,"vote_count":2},{"id":428,"rating":4,"vote_count":18},{"id":429,"rating":5,"vote_count":51},{"id":431,"rating":4,"vote_count":5},{"id":432,"rating":5,"vote_count":22},{"id":433,"rating":4,"vote_count":41},{"id":434,"rating":4,"vote_count":32},{"id":435,"rating":4,"vote_count":3},{"id":436,"rating":5,"vote_count":45},{"id":437,"rating":5,"vote_count":13},{"id":438,"rating":4,"vote_count":2},{"id":439,"rating":5,"vote_count":56},{"id":440,"rating":3,"vote_count":21},{"id":441,"rating":4,"vote_count":63},{"id":442,"rating":5,"vote_count":22},{"id":443,"rating":5,"vote_count":18},{"id":444,"rating":4,"vote_count":38},{"id":445,"rating":3,"vote_count":5},{"id":446,"rating":4,"vote_count":7},{"id":447,"rating":5,"vote_count":3},{"id":448,"rating":4,"vote_count":5},{"id":449,"rating":5,"vote_count":8},{"id":450,"rating":5,"vote_count":30},{"id":451,"rating":4,"vote_count":39},{"id":452,"rating":4,"vote_count":4},{"id":453,"rating":4,"vote_count":70},{"id":454,"rating":5,"vote_count":10},{"id":455,"rating":5,"vote_count":395},{"id":456,"rating":5,"vote_count":2},{"id":458,"rating":5,"vote_count":16},{"id":459,"rating":5,"vote_count":6},{"id":460,"rating":5,"vote_count":154},{"id":461,"rating":5,"vote_count":88},{"id":462,"rating":4,"vote_count":37},{"id":523,"rating":5,"vote_count":18},{"id":463,"rating":5,"vote_count":221},{"id":464,"rating":4,"vote_count":5},{"id":465,"rating":5,"vote_count":46},{"id":466,"rating":5,"vote_count":26},{"id":472,"rating":5,"vote_count":965},{"id":467,"rating":5,"vote_count":308},{"id":468,"rating":5,"vote_count":50},{"id":469,"rating":3,"vote_count":3},{"id":470,"rating":5,"vote_count":15},{"id":471,"rating":4,"vote_count":18},{"id":473,"rating":5,"vote_count":8},{"id":474,"rating":5,"vote_count":19},{"id":475,"rating":4,"vote_count":7},{"id":476,"rating":5,"vote_count":141},{"id":586,"rating":4,"vote_count":13},{"id":477,"rating":5,"vote_count":13},{"id":478,"rating":4,"vote_count":5},{"id":479,"rating":4,"vote_count":8},{"id":480,"rating":4,"vote_count":8},{"id":481,"rating":5,"vote_count":17},{"id":579,"rating":4,"vote_count":5},{"id":482,"rating":4,"vote_count":13},{"id":483,"rating":5,"vote_count":151},{"id":484,"rating":5,"vote_count":21},{"id":485,"rating":5,"vote_count":20},{"id":486,"rating":5,"vote_count":9},{"id":487,"rating":4,"vote_count":42},{"id":488,"rating":5,"vote_count":3},{"id":489,"rating":5,"vote_count":248},{"id":490,"rating":4,"vote_count":10},{"id":505,"rating":5,"vote_count":111},{"id":491,"rating":4,"vote_count":5},{"id":492,"rating":4,"vote_count":75},{"id":493,"rating":4,"vote_count":150},{"id":494,"rating":5,"vote_count":28},{"id":495,"rating":4,"vote_count":1},{"id":496,"rating":5,"vote_count":3},{"id":497,"rating":5,"vote_count":352},{"id":498,"rating":5,"vote_count":14},{"id":499,"rating":5,"vote_count":341},{"id":517,"rating":5,"vote_count":2},{"id":500,"rating":5,"vote_count":176},{"id":501,"rating":5,"vote_count":110},{"id":502,"rating":5,"vote_count":36},{"id":503,"rating":5,"vote_count":160},{"id":504,"rating":4,"vote_count":2},{"id":506,"rating":5,"vote_count":52},{"id":507,"rating":4,"vote_count":77},{"id":508,"rating":5,"vote_count":61},{"id":509,"rating":5,"vote_count":38},{"id":510,"rating":4,"vote_count":16},{"id":511,"rating":4,"vote_count":22},{"id":512,"rating":4,"vote_count":5},{"id":513,"rating":4,"vote_count":56},{"id":514,"rating":5,"vote_count":60},{"id":515,"rating":5,"vote_count":16},{"id":516,"rating":5,"vote_count":21},{"id":518,"rating":3,"vote_count":1},{"id":519,"rating":4,"vote_count":8},{"id":520,"rating":4,"vote_count":10},{"id":521,"rating":4,"vote_count":15},{"id":522,"rating":5,"vote_count":30},{"id":524,"rating":3,"vote_count":4},{"id":525,"rating":5,"vote_count":31},{"id":526,"rating":5,"vote_count":90},{"id":527,"rating":5,"vote_count":17},{"id":594,"rating":4,"vote_count":7},{"id":528,"rating":4,"vote_count":12},{"id":529,"rating":4,"vote_count":32},{"id":530,"rating":4,"vote_count":10},{"id":531,"rating":4,"vote_count":44},{"id":532,"rating":4,"vote_count":42},{"id":533,"rating":5,"vote_count":21},{"id":1230,"rating":4,"vote_count":12},{"id":534,"rating":4,"vote_count":6},{"id":535,"rating":5,"vote_count":336},{"id":536,"rating":4,"vote_count":45},{"id":537,"rating":4,"vote_count":22},{"id":538,"rating":4,"vote_count":51},{"id":539,"rating":5,"vote_count":284},{"id":540,"rating":5,"vote_count":10},{"id":541,"rating":3,"vote_count":2},{"id":542,"rating":5,"vote_count":2},{"id":543,"rating":4,"vote_count":12},{"id":544,"rating":4,"vote_count":61},{"id":545,"rating":5,"vote_count":5},{"id":546,"rating":5,"vote_count":8},{"id":547,"rating":4,"vote_count":29},{"id":548,"rating":5,"vote_count":6},{"id":1046,"rating":5,"vote_count":11},{"id":549,"rating":4,"vote_count":246},{"id":550,"rating":5,"vote_count":2},{"id":551,"rating":4,"vote_count":67},{"id":552,"rating":3,"vote_count":6},{"id":553,"rating":5,"vote_count":21},{"id":554,"rating":5,"vote_count":4},{"id":555,"rating":4,"vote_count":9},{"id":556,"rating":5,"vote_count":22},{"id":557,"rating":4,"vote_count":14},{"id":558,"rating":5,"vote_count":4},{"id":559,"rating":4,"vote_count":8},{"id":560,"rating":5,"vote_count":99},{"id":561,"rating":5,"vote_count":1},{"id":562,"rating":4,"vote_count":1},{"id":563,"rating":4,"vote_count":8},{"id":564,"rating":4,"vote_count":14},{"id":565,"rating":5,"vote_count":16},{"id":566,"rating":4,"vote_count":15},{"id":567,"rating":4,"vote_count":65},{"id":568,"rating":4,"vote_count":19},{"id":569,"rating":5,"vote_count":3},{"id":570,"rating":4,"vote_count":1},{"id":571,"rating":5,"vote_count":93},{"id":572,"rating":4,"vote_count":3},{"id":573,"rating":5,"vote_count":28},{"id":574,"rating":5,"vote_count":7},{"id":575,"rating":5,"vote_count":1},{"id":576,"rating":4,"vote_count":6},{"id":577,"rating":5,"vote_count":106},{"id":578,"rating":4,"vote_count":3},{"id":580,"rating":5,"vote_count":1},{"id":581,"rating":5,"vote_count":37},{"id":582,"rating":5,"vote_count":38},{"id":583,"rating":4,"vote_count":20},{"id":584,"rating":4,"vote_count":14},{"id":585,"rating":4,"vote_count":13},{"id":587,"rating":5,"vote_count":11},{"id":588,"rating":4,"vote_count":13},{"id":589,"rating":5,"vote_count":17},{"id":590,"rating":4,"vote_count":16},{"id":591,"rating":5,"vote_count":15},{"id":592,"rating":4,"vote_count":8},{"id":593,"rating":5,"vote_count":10},{"id":595,"rating":5,"vote_count":13},{"id":596,"rating":4,"vote_count":13},{"id":597,"rating":4,"vote_count":9},{"id":598,"rating":5,"vote_count":77},{"id":599,"rating":5,"vote_count":308},{"id":600,"rating":5,"vote_count":264},{"id":601,"rating":5,"vote_count":168},{"id":602,"rating":5,"vote_count":507},{"id":603,"rating":4,"vote_count":2},{"id":604,"rating":5,"vote_count":83},{"id":605,"rating":5,"vote_count":11},{"id":606,"rating":5,"vote_count":5},{"id":607,"rating":4,"vote_count":45},{"id":608,"rating":4,"vote_count":28},{"id":609,"rating":5,"vote_count":7},{"id":853,"rating":4,"vote_count":103},{"id":610,"rating":4,"vote_count":51},{"id":611,"rating":4,"vote_count":76},{"id":612,"rating":4,"vote_count":32},{"id":613,"rating":4,"vote_count":8},{"id":623,"rating":4,"vote_count":27},{"id":614,"rating":4,"vote_count":19},{"id":615,"rating":5,"vote_count":24},{"id":616,"rating":4,"vote_count":45},{"id":617,"rating":5,"vote_count":6},{"id":630,"rating":4,"vote_count":81},{"id":618,"rating":5,"vote_count":148},{"id":619,"rating":4,"vote_count":8},{"id":620,"rating":5,"vote_count":131},{"id":621,"rating":4,"vote_count":17},{"id":622,"rating":4,"vote_count":80},{"id":1231,"rating":5,"vote_count":18},{"id":624,"rating":5,"vote_count":15},{"id":625,"rating":4,"vote_count":26},{"id":626,"rating":5,"vote_count":2},{"id":627,"rating":4,"vote_count":30},{"id":628,"rating":5,"vote_count":58},{"id":629,"rating":4,"vote_count":41},{"id":631,"rating":3,"vote_count":2},{"id":632,"rating":4,"vote_count":147},{"id":633,"rating":3,"vote_count":19},{"id":634,"rating":5,"vote_count":3},{"id":635,"rating":4,"vote_count":66},{"id":1078,"rating":5,"vote_count":10},{"id":636,"rating":4,"vote_count":31},{"id":637,"rating":5,"vote_count":64},{"id":638,"rating":4,"vote_count":15},{"id":639,"rating":5,"vote_count":35},{"id":640,"rating":5,"vote_count":11},{"id":641,"rating":4,"vote_count":3},{"id":642,"rating":4,"vote_count":21},{"id":643,"rating":4,"vote_count":54},{"id":644,"rating":5,"vote_count":66},{"id":645,"rating":5,"vote_count":38},{"id":732,"rating":5,"vote_count":6},{"id":646,"rating":4,"vote_count":79},{"id":647,"rating":4,"vote_count":18},{"id":648,"rating":5,"vote_count":17},{"id":649,"rating":5,"vote_count":8},{"id":654,"rating":5,"vote_count":76},{"id":650,"rating":5,"vote_count":20},{"id":651,"rating":5,"vote_count":2},{"id":652,"rating":5,"vote_count":91},{"id":653,"rating":4,"vote_count":9},{"id":655,"rating":5,"vote_count":468},{"id":656,"rating":5,"vote_count":13},{"id":657,"rating":5,"vote_count":6},{"id":658,"rating":4,"vote_count":19},{"id":659,"rating":5,"vote_count":2},{"id":692,"rating":5,"vote_count":244},{"id":660,"rating":4,"vote_count":25},{"id":661,"rating":5,"vote_count":6},{"id":662,"rating":4,"vote_count":18},{"id":663,"rating":5,"vote_count":266},{"id":733,"rating":5,"vote_count":5},{"id":664,"rating":5,"vote_count":299},{"id":665,"rating":4,"vote_count":142},{"id":666,"rating":4,"vote_count":166},{"id":667,"rating":4,"vote_count":367},{"id":668,"rating":5,"vote_count":536},{"id":1092,"rating":5,"vote_count":53},{"id":669,"rating":5,"vote_count":196},{"id":670,"rating":5,"vote_count":144},{"id":671,"rating":4,"vote_count":158},{"id":672,"rating":5,"vote_count":293},{"id":673,"rating":4,"vote_count":175},{"id":674,"rating":4,"vote_count":139},{"id":675,"rating":5,"vote_count":108},{"id":676,"rating":5,"vote_count":43},{"id":677,"rating":5,"vote_count":40},{"id":678,"rating":4,"vote_count":38},{"id":1173,"rating":4,"vote_count":20},{"id":679,"rating":4,"vote_count":118},{"id":680,"rating":5,"vote_count":27},{"id":681,"rating":5,"vote_count":9},{"id":682,"rating":5,"vote_count":129},{"id":693,"rating":5,"vote_count":5},{"id":683,"rating":5,"vote_count":50},{"id":684,"rating":5,"vote_count":32},{"id":685,"rating":4,"vote_count":11},{"id":686,"rating":4,"vote_count":45},{"id":687,"rating":4,"vote_count":19},{"id":1536,"rating":5,"vote_count":2},{"id":688,"rating":4,"vote_count":7},{"id":689,"rating":5,"vote_count":2},{"id":690,"rating":4,"vote_count":9},{"id":691,"rating":5,"vote_count":4},{"id":704,"rating":4,"vote_count":2},{"id":694,"rating":5,"vote_count":291},{"id":695,"rating":5,"vote_count":12},{"id":696,"rating":5,"vote_count":45},{"id":697,"rating":5,"vote_count":30},{"id":698,"rating":5,"vote_count":7},{"id":699,"rating":5,"vote_count":20},{"id":700,"rating":5,"vote_count":23},{"id":701,"rating":5,"vote_count":150},{"id":702,"rating":4,"vote_count":10},{"id":703,"rating":4,"vote_count":142},{"id":705,"rating":5,"vote_count":39},{"id":706,"rating":4,"vote_count":45},{"id":707,"rating":4,"vote_count":5},{"id":708,"rating":5,"vote_count":18},{"id":709,"rating":5,"vote_count":81},{"id":710,"rating":5,"vote_count":605},{"id":711,"rating":5,"vote_count":204},{"id":712,"rating":5,"vote_count":181},{"id":713,"rating":5,"vote_count":169},{"id":714,"rating":5,"vote_count":174},{"id":715,"rating":5,"vote_count":161},{"id":716,"rating":5,"vote_count":54},{"id":717,"rating":5,"vote_count":44},{"id":718,"rating":5,"vote_count":53},{"id":719,"rating":5,"vote_count":56},{"id":720,"rating":5,"vote_count":37},{"id":721,"rating":5,"vote_count":70},{"id":722,"rating":5,"vote_count":32},{"id":723,"rating":4,"vote_count":35},{"id":724,"rating":5,"vote_count":37},{"id":725,"rating":5,"vote_count":36},{"id":726,"rating":5,"vote_count":35},{"id":1537,"rating":4,"vote_count":5},{"id":727,"rating":5,"vote_count":19},{"id":728,"rating":4,"vote_count":87},{"id":729,"rating":4,"vote_count":8},{"id":730,"rating":4,"vote_count":10},{"id":731,"rating":5,"vote_count":4},{"id":793,"rating":5,"vote_count":19},{"id":734,"rating":5,"vote_count":4},{"id":735,"rating":4,"vote_count":1},{"id":736,"rating":4,"vote_count":2},{"id":737,"rating":5,"vote_count":4},{"id":738,"rating":5,"vote_count":10},{"id":820,"rating":5,"vote_count":17},{"id":739,"rating":4,"vote_count":1},{"id":740,"rating":5,"vote_count":1},{"id":741,"rating":5,"vote_count":4},{"id":742,"rating":4,"vote_count":8},{"id":743,"rating":5,"vote_count":1},{"id":744,"rating":5,"vote_count":89},{"id":745,"rating":4,"vote_count":17},{"id":746,"rating":4,"vote_count":9},{"id":747,"rating":4,"vote_count":22},{"id":748,"rating":5,"vote_count":5},{"id":749,"rating":5,"vote_count":4},{"id":750,"rating":5,"vote_count":9},{"id":751,"rating":5,"vote_count":2},{"id":752,"rating":4,"vote_count":8},{"id":753,"rating":4,"vote_count":5},{"id":754,"rating":4,"vote_count":20},{"id":755,"rating":3,"vote_count":5},{"id":1568,"rating":5,"vote_count":4},{"id":756,"rating":4,"vote_count":10},{"id":757,"rating":4,"vote_count":5},{"id":758,"rating":4,"vote_count":16},{"id":759,"rating":4,"vote_count":41},{"id":760,"rating":5,"vote_count":8},{"id":761,"rating":4,"vote_count":6},{"id":762,"rating":5,"vote_count":2},{"id":763,"rating":4,"vote_count":6},{"id":764,"rating":4,"vote_count":14},{"id":765,"rating":5,"vote_count":21},{"id":766,"rating":4,"vote_count":56},{"id":767,"rating":4,"vote_count":24},{"id":1642,"rating":4,"vote_count":2},{"id":768,"rating":4,"vote_count":29},{"id":769,"rating":5,"vote_count":5},{"id":770,"rating":5,"vote_count":41},{"id":771,"rating":5,"vote_count":19},{"id":772,"rating":5,"vote_count":71},{"id":773,"rating":5,"vote_count":4},{"id":774,"rating":5,"vote_count":34},{"id":775,"rating":4,"vote_count":64},{"id":776,"rating":5,"vote_count":438},{"id":777,"rating":4,"vote_count":21},{"id":778,"rating":5,"vote_count":69},{"id":779,"rating":4,"vote_count":141},{"id":780,"rating":5,"vote_count":10},{"id":781,"rating":4,"vote_count":38},{"id":782,"rating":5,"vote_count":899},{"id":783,"rating":4,"vote_count":43},{"id":1232,"rating":4,"vote_count":5},{"id":784,"rating":5,"vote_count":11},{"id":785,"rating":5,"vote_count":63},{"id":786,"rating":4,"vote_count":79},{"id":787,"rating":4,"vote_count":18},{"id":788,"rating":5,"vote_count":30},{"id":789,"rating":5,"vote_count":4},{"id":790,"rating":4,"vote_count":15},{"id":791,"rating":5,"vote_count":4},{"id":792,"rating":5,"vote_count":60},{"id":794,"rating":4,"vote_count":25},{"id":795,"rating":4,"vote_count":34},{"id":796,"rating":4,"vote_count":30},{"id":797,"rating":5,"vote_count":16},{"id":798,"rating":5,"vote_count":46},{"id":799,"rating":4,"vote_count":24},{"id":800,"rating":4,"vote_count":2},{"id":801,"rating":5,"vote_count":5},{"id":802,"rating":4,"vote_count":33},{"id":803,"rating":4,"vote_count":3},{"id":804,"rating":2,"vote_count":3},{"id":805,"rating":5,"vote_count":57},{"id":806,"rating":5,"vote_count":94},{"id":807,"rating":5,"vote_count":6},{"id":808,"rating":5,"vote_count":793},{"id":809,"rating":4,"vote_count":59},{"id":810,"rating":5,"vote_count":456},{"id":811,"rating":4,"vote_count":128},{"id":812,"rating":5,"vote_count":632},{"id":813,"rating":4,"vote_count":371},{"id":814,"rating":4,"vote_count":108},{"id":815,"rating":4,"vote_count":84},{"id":816,"rating":5,"vote_count":89},{"id":817,"rating":5,"vote_count":16},{"id":818,"rating":4,"vote_count":10},{"id":819,"rating":5,"vote_count":2},{"id":821,"rating":5,"vote_count":103},{"id":822,"rating":5,"vote_count":7},{"id":823,"rating":4,"vote_count":2},{"id":824,"rating":5,"vote_count":260},{"id":825,"rating":5,"vote_count":43},{"id":826,"rating":4,"vote_count":9},{"id":827,"rating":4,"vote_count":21},{"id":828,"rating":5,"vote_count":38},{"id":829,"rating":5,"vote_count":75},{"id":830,"rating":5,"vote_count":1},{"id":1233,"rating":4,"vote_count":30},{"id":831,"rating":4,"vote_count":33},{"id":832,"rating":5,"vote_count":123},{"id":833,"rating":4,"vote_count":9},{"id":834,"rating":4,"vote_count":15},{"id":835,"rating":4,"vote_count":87},{"id":836,"rating":4,"vote_count":83},{"id":1249,"rating":5,"vote_count":108},{"id":837,"rating":4,"vote_count":7},{"id":838,"rating":4,"vote_count":28},{"id":839,"rating":4,"vote_count":68},{"id":840,"rating":4,"vote_count":12},{"id":841,"rating":3,"vote_count":5},{"id":851,"rating":4,"vote_count":37},{"id":842,"rating":4,"vote_count":24},{"id":843,"rating":5,"vote_count":9},{"id":844,"rating":4,"vote_count":10},{"id":845,"rating":3,"vote_count":38},{"id":852,"rating":4,"vote_count":23},{"id":846,"rating":4,"vote_count":26},{"id":847,"rating":4,"vote_count":9},{"id":848,"rating":4,"vote_count":4},{"id":849,"rating":4,"vote_count":6},{"id":850,"rating":4,"vote_count":26},{"id":854,"rating":5,"vote_count":6},{"id":855,"rating":5,"vote_count":245},{"id":856,"rating":5,"vote_count":13},{"id":857,"rating":5,"vote_count":14},{"id":858,"rating":4,"vote_count":3},{"id":859,"rating":5,"vote_count":55},{"id":860,"rating":5,"vote_count":927},{"id":861,"rating":5,"vote_count":500},{"id":902,"rating":4,"vote_count":15},{"id":862,"rating":5,"vote_count":691},{"id":863,"rating":5,"vote_count":14},{"id":864,"rating":5,"vote_count":3},{"id":865,"rating":5,"vote_count":16},{"id":913,"rating":5,"vote_count":6},{"id":866,"rating":4,"vote_count":138},{"id":867,"rating":5,"vote_count":10},{"id":868,"rating":5,"vote_count":4},{"id":869,"rating":4,"vote_count":33},{"id":870,"rating":5,"vote_count":10},{"id":871,"rating":4,"vote_count":23},{"id":872,"rating":4,"vote_count":20},{"id":873,"rating":4,"vote_count":6},{"id":874,"rating":5,"vote_count":87},{"id":875,"rating":4,"vote_count":12},{"id":876,"rating":5,"vote_count":386},{"id":877,"rating":4,"vote_count":61},{"id":878,"rating":5,"vote_count":181},{"id":879,"rating":4,"vote_count":26},{"id":880,"rating":5,"vote_count":124},{"id":881,"rating":5,"vote_count":197},{"id":882,"rating":4,"vote_count":2},{"id":883,"rating":4,"vote_count":25},{"id":884,"rating":4,"vote_count":28},{"id":885,"rating":3,"vote_count":6},{"id":886,"rating":5,"vote_count":4},{"id":887,"rating":3,"vote_count":6},{"id":888,"rating":4,"vote_count":159},{"id":889,"rating":4,"vote_count":55},{"id":890,"rating":5,"vote_count":250},{"id":891,"rating":4,"vote_count":16},{"id":892,"rating":4,"vote_count":270},{"id":893,"rating":4,"vote_count":90},{"id":894,"rating":4,"vote_count":24},{"id":895,"rating":4,"vote_count":103},{"id":928,"rating":5,"vote_count":15},{"id":896,"rating":4,"vote_count":30},{"id":897,"rating":5,"vote_count":2},{"id":898,"rating":4,"vote_count":48},{"id":899,"rating":4,"vote_count":113},{"id":900,"rating":5,"vote_count":9},{"id":901,"rating":4,"vote_count":15},{"id":903,"rating":4,"vote_count":20},{"id":904,"rating":4,"vote_count":54},{"id":905,"rating":5,"vote_count":2},{"id":906,"rating":4,"vote_count":11},{"id":907,"rating":5,"vote_count":1280},{"id":935,"rating":5,"vote_count":20},{"id":908,"rating":4,"vote_count":25},{"id":909,"rating":4,"vote_count":219},{"id":910,"rating":4,"vote_count":4},{"id":911,"rating":4,"vote_count":137},{"id":912,"rating":4,"vote_count":4},{"id":914,"rating":5,"vote_count":1},{"id":915,"rating":5,"vote_count":11},{"id":916,"rating":5,"vote_count":30},{"id":917,"rating":4,"vote_count":10},{"id":918,"rating":5,"vote_count":60},{"id":919,"rating":4,"vote_count":8},{"id":920,"rating":5,"vote_count":5},{"id":921,"rating":5,"vote_count":13},{"id":922,"rating":3,"vote_count":2},{"id":957,"rating":5,"vote_count":15},{"id":923,"rating":5,"vote_count":35},{"id":924,"rating":4,"vote_count":1},{"id":925,"rating":4,"vote_count":18},{"id":926,"rating":4,"vote_count":60},{"id":927,"rating":5,"vote_count":62},{"id":929,"rating":5,"vote_count":28},{"id":930,"rating":5,"vote_count":33},{"id":931,"rating":4,"vote_count":14},{"id":932,"rating":4,"vote_count":12},{"id":933,"rating":5,"vote_count":4},{"id":934,"rating":4,"vote_count":9},{"id":936,"rating":3,"vote_count":3},{"id":937,"rating":4,"vote_count":4},{"id":938,"rating":4,"vote_count":12},{"id":939,"rating":5,"vote_count":12},{"id":940,"rating":5,"vote_count":6},{"id":941,"rating":5,"vote_count":423},{"id":942,"rating":5,"vote_count":2},{"id":943,"rating":5,"vote_count":11},{"id":944,"rating":4,"vote_count":24},{"id":945,"rating":5,"vote_count":34},{"id":975,"rating":5,"vote_count":10},{"id":946,"rating":4,"vote_count":19},{"id":947,"rating":5,"vote_count":11},{"id":948,"rating":4,"vote_count":19},{"id":949,"rating":5,"vote_count":12},{"id":950,"rating":5,"vote_count":57},{"id":951,"rating":4,"vote_count":7},{"id":952,"rating":5,"vote_count":20},{"id":953,"rating":5,"vote_count":2},{"id":954,"rating":4,"vote_count":4},{"id":955,"rating":5,"vote_count":96},{"id":956,"rating":5,"vote_count":30},{"id":958,"rating":5,"vote_count":12},{"id":959,"rating":5,"vote_count":6},{"id":960,"rating":4,"vote_count":3},{"id":961,"rating":5,"vote_count":25},{"id":962,"rating":5,"vote_count":7},{"id":963,"rating":4,"vote_count":2},{"id":976,"rating":5,"vote_count":2},{"id":964,"rating":4,"vote_count":2},{"id":965,"rating":4,"vote_count":11},{"id":966,"rating":5,"vote_count":1},{"id":967,"rating":5,"vote_count":1},{"id":968,"rating":5,"vote_count":2},{"id":969,"rating":4,"vote_count":13},{"id":1016,"rating":4,"vote_count":7},{"id":970,"rating":5,"vote_count":2},{"id":971,"rating":5,"vote_count":51},{"id":972,"rating":4,"vote_count":18},{"id":973,"rating":4,"vote_count":30},{"id":974,"rating":4,"vote_count":7},{"id":977,"rating":5,"vote_count":1},{"id":978,"rating":5,"vote_count":2},{"id":979,"rating":4,"vote_count":28},{"id":980,"rating":5,"vote_count":3},{"id":981,"rating":5,"vote_count":6},{"id":982,"rating":4,"vote_count":4},{"id":983,"rating":5,"vote_count":8},{"id":984,"rating":5,"vote_count":20},{"id":985,"rating":4,"vote_count":20},{"id":986,"rating":5,"vote_count":14},{"id":987,"rating":4,"vote_count":49},{"id":988,"rating":5,"vote_count":34},{"id":1264,"rating":5,"vote_count":14},{"id":989,"rating":5,"vote_count":88},{"id":990,"rating":5,"vote_count":50},{"id":991,"rating":5,"vote_count":76},{"id":992,"rating":5,"vote_count":1},{"id":993,"rating":5,"vote_count":8},{"id":994,"rating":5,"vote_count":10},{"id":995,"rating":5,"vote_count":1},{"id":996,"rating":4,"vote_count":103},{"id":997,"rating":4,"vote_count":17},{"id":998,"rating":4,"vote_count":31},{"id":999,"rating":4,"vote_count":49},{"id":1000,"rating":5,"vote_count":6},{"id":1001,"rating":5,"vote_count":37},{"id":1002,"rating":4,"vote_count":4},{"id":1003,"rating":5,"vote_count":20},{"id":1004,"rating":5,"vote_count":20},{"id":1005,"rating":5,"vote_count":31},{"id":1006,"rating":5,"vote_count":4},{"id":1007,"rating":5,"vote_count":56},{"id":1008,"rating":5,"vote_count":149},{"id":1009,"rating":5,"vote_count":274},{"id":1010,"rating":5,"vote_count":361},{"id":1047,"rating":5,"vote_count":11},{"id":1011,"rating":4,"vote_count":4},{"id":1012,"rating":5,"vote_count":2},{"id":1013,"rating":4,"vote_count":8},{"id":1014,"rating":4,"vote_count":10},{"id":1015,"rating":4,"vote_count":35},{"id":1017,"rating":4,"vote_count":5},{"id":1018,"rating":5,"vote_count":3},{"id":1019,"rating":4,"vote_count":126},{"id":1020,"rating":5,"vote_count":225},{"id":1021,"rating":5,"vote_count":16},{"id":1039,"rating":3,"vote_count":13},{"id":1022,"rating":4,"vote_count":150},{"id":1023,"rating":5,"vote_count":73},{"id":1024,"rating":5,"vote_count":2},{"id":1025,"rating":4,"vote_count":34},{"id":1026,"rating":3,"vote_count":2},{"id":1027,"rating":4,"vote_count":58},{"id":1028,"rating":5,"vote_count":8},{"id":1029,"rating":5,"vote_count":63},{"id":1045,"rating":5,"vote_count":16},{"id":1030,"rating":5,"vote_count":2},{"id":1031,"rating":5,"vote_count":55},{"id":1032,"rating":5,"vote_count":35},{"id":1033,"rating":5,"vote_count":9},{"id":1034,"rating":5,"vote_count":33},{"id":1035,"rating":5,"vote_count":31},{"id":1036,"rating":5,"vote_count":12},{"id":1037,"rating":5,"vote_count":24},{"id":1038,"rating":4,"vote_count":7},{"id":1040,"rating":5,"vote_count":479},{"id":1041,"rating":5,"vote_count":45},{"id":1042,"rating":4,"vote_count":8},{"id":1043,"rating":5,"vote_count":10},{"id":1044,"rating":3,"vote_count":24},{"id":1048,"rating":3,"vote_count":12},{"id":1049,"rating":5,"vote_count":256},{"id":1050,"rating":4,"vote_count":14},{"id":1051,"rating":4,"vote_count":7},{"id":1052,"rating":4,"vote_count":6},{"id":1053,"rating":5,"vote_count":526},{"id":1054,"rating":4,"vote_count":32},{"id":1055,"rating":4,"vote_count":138},{"id":1056,"rating":5,"vote_count":47},{"id":1057,"rating":4,"vote_count":12},{"id":1058,"rating":4,"vote_count":37},{"id":1059,"rating":5,"vote_count":92},{"id":1060,"rating":4,"vote_count":12},{"id":1061,"rating":5,"vote_count":32},{"id":1062,"rating":5,"vote_count":7},{"id":1063,"rating":4,"vote_count":22},{"id":1064,"rating":5,"vote_count":48},{"id":1065,"rating":5,"vote_count":3},{"id":1066,"rating":5,"vote_count":3},{"id":1076,"rating":4,"vote_count":4},{"id":1067,"rating":4,"vote_count":21},{"id":1068,"rating":5,"vote_count":2},{"id":1069,"rating":5,"vote_count":17},{"id":1070,"rating":5,"vote_count":7},{"id":1077,"rating":5,"vote_count":6},{"id":1071,"rating":5,"vote_count":7},{"id":1072,"rating":5,"vote_count":89},{"id":1073,"rating":4,"vote_count":5},{"id":1074,"rating":5,"vote_count":16},{"id":1075,"rating":5,"vote_count":11},{"id":1079,"rating":5,"vote_count":5},{"id":1080,"rating":4,"vote_count":31},{"id":1081,"rating":4,"vote_count":5},{"id":1082,"rating":5,"vote_count":37},{"id":1083,"rating":4,"vote_count":24},{"id":1084,"rating":5,"vote_count":18},{"id":1085,"rating":5,"vote_count":7},{"id":1086,"rating":4,"vote_count":5},{"id":1087,"rating":4,"vote_count":9},{"id":1088,"rating":5,"vote_count":10},{"id":1089,"rating":5,"vote_count":1},{"id":1090,"rating":5,"vote_count":7},{"id":1091,"rating":5,"vote_count":22},{"id":1093,"rating":1,"vote_count":1},{"id":1094,"rating":5,"vote_count":6},{"id":1095,"rating":5,"vote_count":2},{"id":1096,"rating":5,"vote_count":16},{"id":1097,"rating":5,"vote_count":1},{"id":1098,"rating":5,"vote_count":5},{"id":1099,"rating":4,"vote_count":7},{"id":1100,"rating":5,"vote_count":8},{"id":1101,"rating":4,"vote_count":8},{"id":1102,"rating":4,"vote_count":13},{"id":1103,"rating":4,"vote_count":32},{"id":1125,"rating":4,"vote_count":5},{"id":1104,"rating":5,"vote_count":88},{"id":1105,"rating":5,"vote_count":33},{"id":1106,"rating":4,"vote_count":21},{"id":1107,"rating":5,"vote_count":15},{"id":1108,"rating":4,"vote_count":13},{"id":1126,"rating":5,"vote_count":9},{"id":1109,"rating":4,"vote_count":24},{"id":1110,"rating":5,"vote_count":58},{"id":1111,"rating":5,"vote_count":3},{"id":1112,"rating":5,"vote_count":6},{"id":1113,"rating":5,"vote_count":45},{"id":1114,"rating":5,"vote_count":5},{"id":1115,"rating":5,"vote_count":20},{"id":1116,"rating":4,"vote_count":19},{"id":1117,"rating":5,"vote_count":9},{"id":1118,"rating":4,"vote_count":29},{"id":1119,"rating":5,"vote_count":27},{"id":1120,"rating":5,"vote_count":710},{"id":1121,"rating":4,"vote_count":61},{"id":1122,"rating":4,"vote_count":33},{"id":1123,"rating":4,"vote_count":2},{"id":1124,"rating":5,"vote_count":23},{"id":1127,"rating":5,"vote_count":162},{"id":1128,"rating":5,"vote_count":43},{"id":1129,"rating":5,"vote_count":26},{"id":1130,"rating":3,"vote_count":1},{"id":1155,"rating":5,"vote_count":5},{"id":1131,"rating":4,"vote_count":60},{"id":1132,"rating":4,"vote_count":6},{"id":1133,"rating":5,"vote_count":1},{"id":1134,"rating":5,"vote_count":2},{"id":1135,"rating":5,"vote_count":11},{"id":1136,"rating":5,"vote_count":1},{"id":1137,"rating":5,"vote_count":5},{"id":1138,"rating":5,"vote_count":4},{"id":1139,"rating":5,"vote_count":20},{"id":1156,"rating":5,"vote_count":102},{"id":1140,"rating":5,"vote_count":3},{"id":1141,"rating":5,"vote_count":4},{"id":1142,"rating":4,"vote_count":4},{"id":1143,"rating":4,"vote_count":8},{"id":1144,"rating":5,"vote_count":30},{"id":1275,"rating":5,"vote_count":7},{"id":1145,"rating":5,"vote_count":6},{"id":1146,"rating":5,"vote_count":2},{"id":1147,"rating":5,"vote_count":12},{"id":1148,"rating":5,"vote_count":9},{"id":1149,"rating":5,"vote_count":29},{"id":1150,"rating":4,"vote_count":6},{"id":1151,"rating":5,"vote_count":16},{"id":1152,"rating":5,"vote_count":9},{"id":1153,"rating":5,"vote_count":7},{"id":1154,"rating":5,"vote_count":48},{"id":1157,"rating":4,"vote_count":32},{"id":1158,"rating":5,"vote_count":36},{"id":1159,"rating":4,"vote_count":13},{"id":1160,"rating":5,"vote_count":114},{"id":1161,"rating":4,"vote_count":22},{"id":1162,"rating":5,"vote_count":460},{"id":1163,"rating":5,"vote_count":430},{"id":1164,"rating":5,"vote_count":117},{"id":1165,"rating":5,"vote_count":4},{"id":1166,"rating":3,"vote_count":4},{"id":1167,"rating":5,"vote_count":6},{"id":1168,"rating":5,"vote_count":115},{"id":1169,"rating":5,"vote_count":116},{"id":1170,"rating":4,"vote_count":13},{"id":1171,"rating":5,"vote_count":6},{"id":1172,"rating":5,"vote_count":9},{"id":1174,"rating":5,"vote_count":24},{"id":1175,"rating":4,"vote_count":5},{"id":1176,"rating":5,"vote_count":8},{"id":1177,"rating":5,"vote_count":5},{"id":1178,"rating":3,"vote_count":5},{"id":1216,"rating":4,"vote_count":29},{"id":1179,"rating":5,"vote_count":22},{"id":1180,"rating":5,"vote_count":9},{"id":1181,"rating":4,"vote_count":5},{"id":1182,"rating":4,"vote_count":1},{"id":1183,"rating":5,"vote_count":16},{"id":1184,"rating":5,"vote_count":12},{"id":1185,"rating":4,"vote_count":6},{"id":1186,"rating":5,"vote_count":5},{"id":1187,"rating":5,"vote_count":2},{"id":1188,"rating":5,"vote_count":2},{"id":1189,"rating":5,"vote_count":23},{"id":1190,"rating":5,"vote_count":2},{"id":1191,"rating":5,"vote_count":171},{"id":1192,"rating":5,"vote_count":18},{"id":1193,"rating":5,"vote_count":15},{"id":1194,"rating":5,"vote_count":7},{"id":1195,"rating":5,"vote_count":9},{"id":1196,"rating":5,"vote_count":3},{"id":1197,"rating":5,"vote_count":9},{"id":1281,"rating":5,"vote_count":1},{"id":1198,"rating":5,"vote_count":12},{"id":1199,"rating":5,"vote_count":2},{"id":1200,"rating":5,"vote_count":32},{"id":1201,"rating":5,"vote_count":4},{"id":1202,"rating":5,"vote_count":28},{"id":1506,"rating":5,"vote_count":21},{"id":1203,"rating":5,"vote_count":1},{"id":1204,"rating":5,"vote_count":6},{"id":1205,"rating":4,"vote_count":3},{"id":1206,"rating":4,"vote_count":15},{"id":1207,"rating":4,"vote_count":23},{"id":1208,"rating":5,"vote_count":28},{"id":1209,"rating":4,"vote_count":100},{"id":1210,"rating":5,"vote_count":36},{"id":1211,"rating":5,"vote_count":1},{"id":1217,"rating":1,"vote_count":1},{"id":1212,"rating":4,"vote_count":2},{"id":1213,"rating":5,"vote_count":4},{"id":1214,"rating":5,"vote_count":79},{"id":1215,"rating":3,"vote_count":5},{"id":1227,"rating":4,"vote_count":10},{"id":1218,"rating":4,"vote_count":8},{"id":1219,"rating":5,"vote_count":4},{"id":1220,"rating":5,"vote_count":3},{"id":1221,"rating":3,"vote_count":9},{"id":1222,"rating":5,"vote_count":4},{"id":1223,"rating":4,"vote_count":11},{"id":1224,"rating":3,"vote_count":7},{"id":1225,"rating":5,"vote_count":4},{"id":1226,"rating":5,"vote_count":1},{"id":1234,"rating":4,"vote_count":53},{"id":1235,"rating":4,"vote_count":38},{"id":1236,"rating":4,"vote_count":20},{"id":1237,"rating":4,"vote_count":62},{"id":1238,"rating":5,"vote_count":9},{"id":1239,"rating":4,"vote_count":3},{"id":1240,"rating":5,"vote_count":286},{"id":1241,"rating":4,"vote_count":18},{"id":1242,"rating":5,"vote_count":61},{"id":1243,"rating":4,"vote_count":1},{"id":1244,"rating":4,"vote_count":49},{"id":1245,"rating":5,"vote_count":63},{"id":1246,"rating":5,"vote_count":20},{"id":1247,"rating":5,"vote_count":3},{"id":1248,"rating":5,"vote_count":2},{"id":1250,"rating":5,"vote_count":188},{"id":1251,"rating":5,"vote_count":17},{"id":1252,"rating":5,"vote_count":2},{"id":1253,"rating":5,"vote_count":70},{"id":1254,"rating":4,"vote_count":42},{"id":1655,"rating":5,"vote_count":12},{"id":1255,"rating":3,"vote_count":2},{"id":1256,"rating":5,"vote_count":5},{"id":1257,"rating":5,"vote_count":1},{"id":1258,"rating":4,"vote_count":36},{"id":1302,"rating":5,"vote_count":245},{"id":1259,"rating":4,"vote_count":17},{"id":1260,"rating":4,"vote_count":18},{"id":1261,"rating":4,"vote_count":54},{"id":1262,"rating":4,"vote_count":11},{"id":1263,"rating":5,"vote_count":2},{"id":1320,"rating":5,"vote_count":1},{"id":1265,"rating":4,"vote_count":33},{"id":1266,"rating":5,"vote_count":5},{"id":1267,"rating":4,"vote_count":20},{"id":1268,"rating":4,"vote_count":12},{"id":1269,"rating":5,"vote_count":19},{"id":1270,"rating":4,"vote_count":288},{"id":1271,"rating":4,"vote_count":38},{"id":1272,"rating":5,"vote_count":20},{"id":1273,"rating":3,"vote_count":9},{"id":1274,"rating":5,"vote_count":56},{"id":1276,"rating":5,"vote_count":278},{"id":1277,"rating":5,"vote_count":11},{"id":1278,"rating":5,"vote_count":4},{"id":1279,"rating":5,"vote_count":10},{"id":1280,"rating":4,"vote_count":23},{"id":1282,"rating":5,"vote_count":3},{"id":1283,"rating":4,"vote_count":245},{"id":1284,"rating":4,"vote_count":8},{"id":1285,"rating":5,"vote_count":23},{"id":1286,"rating":4,"vote_count":13},{"id":1287,"rating":4,"vote_count":10},{"id":1288,"rating":5,"vote_count":1125},{"id":1289,"rating":4,"vote_count":1},{"id":1290,"rating":4,"vote_count":2},{"id":1291,"rating":5,"vote_count":11},{"id":1292,"rating":5,"vote_count":41},{"id":1293,"rating":4,"vote_count":1},{"id":1294,"rating":5,"vote_count":49},{"id":1295,"rating":5,"vote_count":48},{"id":1296,"rating":5,"vote_count":30},{"id":1321,"rating":5,"vote_count":2},{"id":1297,"rating":5,"vote_count":14},{"id":1298,"rating":5,"vote_count":65},{"id":1299,"rating":4,"vote_count":201},{"id":1300,"rating":4,"vote_count":30},{"id":1301,"rating":4,"vote_count":202},{"id":1303,"rating":5,"vote_count":2},{"id":1304,"rating":5,"vote_count":42},{"id":1305,"rating":5,"vote_count":3},{"id":1306,"rating":4,"vote_count":8},{"id":1307,"rating":4,"vote_count":105},{"id":1322,"rating":5,"vote_count":35},{"id":1308,"rating":5,"vote_count":53},{"id":1309,"rating":4,"vote_count":61},{"id":1310,"rating":5,"vote_count":25},{"id":1311,"rating":4,"vote_count":21},{"id":1312,"rating":5,"vote_count":88},{"id":1313,"rating":5,"vote_count":291},{"id":1314,"rating":5,"vote_count":4},{"id":1315,"rating":5,"vote_count":88},{"id":1316,"rating":4,"vote_count":42},{"id":1317,"rating":4,"vote_count":118},{"id":1318,"rating":4,"vote_count":24},{"id":1319,"rating":4,"vote_count":12},{"id":1323,"rating":4,"vote_count":37},{"id":1324,"rating":5,"vote_count":16},{"id":1325,"rating":2,"vote_count":3},{"id":1326,"rating":5,"vote_count":43},{"id":1327,"rating":1,"vote_count":1},{"id":1344,"rating":4,"vote_count":2},{"id":1328,"rating":4,"vote_count":3},{"id":1329,"rating":5,"vote_count":2},{"id":1330,"rating":4,"vote_count":8},{"id":1331,"rating":5,"vote_count":1},{"id":1345,"rating":5,"vote_count":18},{"id":1332,"rating":4,"vote_count":1},{"id":1333,"rating":5,"vote_count":22},{"id":1334,"rating":4,"vote_count":68},{"id":1335,"rating":5,"vote_count":2},{"id":1336,"rating":5,"vote_count":20},{"id":1337,"rating":5,"vote_count":10},{"id":1338,"rating":5,"vote_count":11},{"id":1339,"rating":4,"vote_count":21},{"id":1340,"rating":3,"vote_count":15},{"id":1341,"rating":4,"vote_count":56},{"id":1342,"rating":5,"vote_count":18},{"id":1343,"rating":5,"vote_count":19},{"id":1346,"rating":5,"vote_count":17},{"id":1347,"rating":4,"vote_count":15},{"id":1348,"rating":4,"vote_count":8},{"id":1349,"rating":4,"vote_count":1},{"id":1350,"rating":4,"vote_count":12},{"id":1351,"rating":3,"vote_count":24},{"id":1352,"rating":4,"vote_count":8},{"id":1353,"rating":4,"vote_count":6},{"id":1354,"rating":4,"vote_count":36},{"id":1355,"rating":4,"vote_count":8},{"id":1356,"rating":4,"vote_count":17},{"id":1357,"rating":5,"vote_count":63},{"id":1358,"rating":4,"vote_count":15},{"id":1359,"rating":4,"vote_count":42},{"id":1360,"rating":5,"vote_count":4},{"id":1361,"rating":3,"vote_count":15},{"id":1362,"rating":5,"vote_count":38},{"id":1398,"rating":5,"vote_count":26},{"id":1363,"rating":4,"vote_count":2},{"id":1364,"rating":5,"vote_count":7},{"id":1365,"rating":4,"vote_count":6},{"id":1366,"rating":5,"vote_count":10},{"id":1367,"rating":4,"vote_count":47},{"id":1667,"rating":5,"vote_count":40},{"id":1368,"rating":5,"vote_count":7},{"id":1369,"rating":5,"vote_count":48},{"id":1370,"rating":5,"vote_count":33},{"id":1371,"rating":4,"vote_count":28},{"id":1372,"rating":4,"vote_count":6},{"id":1373,"rating":4,"vote_count":5},{"id":1374,"rating":4,"vote_count":5},{"id":1375,"rating":4,"vote_count":5},{"id":1376,"rating":5,"vote_count":13},{"id":1377,"rating":5,"vote_count":2},{"id":1685,"rating":3,"vote_count":17},{"id":1378,"rating":4,"vote_count":10},{"id":1379,"rating":4,"vote_count":3},{"id":1380,"rating":5,"vote_count":39},{"id":1381,"rating":5,"vote_count":5},{"id":1382,"rating":4,"vote_count":3},{"id":1507,"rating":4,"vote_count":12},{"id":1383,"rating":5,"vote_count":7},{"id":1384,"rating":4,"vote_count":27},{"id":1385,"rating":4,"vote_count":17},{"id":1386,"rating":4,"vote_count":113},{"id":1387,"rating":4,"vote_count":27},{"id":1388,"rating":4,"vote_count":3},{"id":1389,"rating":4,"vote_count":37},{"id":1390,"rating":5,"vote_count":9},{"id":1391,"rating":5,"vote_count":175},{"id":1392,"rating":5,"vote_count":4},{"id":1508,"rating":5,"vote_count":6},{"id":1393,"rating":5,"vote_count":40},{"id":1394,"rating":5,"vote_count":31},{"id":1395,"rating":4,"vote_count":40},{"id":1396,"rating":5,"vote_count":20},{"id":1397,"rating":4,"vote_count":14},{"id":1686,"rating":3,"vote_count":10},{"id":1399,"rating":4,"vote_count":31},{"id":1400,"rating":5,"vote_count":3},{"id":1401,"rating":5,"vote_count":38},{"id":1402,"rating":4,"vote_count":19},{"id":1403,"rating":5,"vote_count":3},{"id":1509,"rating":5,"vote_count":2},{"id":1404,"rating":5,"vote_count":45},{"id":1405,"rating":5,"vote_count":82},{"id":1406,"rating":5,"vote_count":9},{"id":1407,"rating":4,"vote_count":33},{"id":1408,"rating":5,"vote_count":275},{"id":1409,"rating":5,"vote_count":13},{"id":1410,"rating":5,"vote_count":19},{"id":1411,"rating":4,"vote_count":31},{"id":1412,"rating":5,"vote_count":314},{"id":1413,"rating":5,"vote_count":48},{"id":1414,"rating":4,"vote_count":19},{"id":1415,"rating":5,"vote_count":726},{"id":1416,"rating":5,"vote_count":634},{"id":1417,"rating":5,"vote_count":492},{"id":1418,"rating":5,"vote_count":368},{"id":1419,"rating":3,"vote_count":23},{"id":1420,"rating":4,"vote_count":95},{"id":1421,"rating":3,"vote_count":4},{"id":1422,"rating":5,"vote_count":88},{"id":1423,"rating":5,"vote_count":31},{"id":1424,"rating":5,"vote_count":29},{"id":1425,"rating":4,"vote_count":62},{"id":1426,"rating":5,"vote_count":118},{"id":1427,"rating":5,"vote_count":839},{"id":1428,"rating":4,"vote_count":45},{"id":1429,"rating":4,"vote_count":7},{"id":1430,"rating":4,"vote_count":43},{"id":1431,"rating":5,"vote_count":90},{"id":1432,"rating":5,"vote_count":154},{"id":1433,"rating":5,"vote_count":21},{"id":1434,"rating":4,"vote_count":19},{"id":1435,"rating":4,"vote_count":49},{"id":1436,"rating":4,"vote_count":22},{"id":1437,"rating":4,"vote_count":14},{"id":1438,"rating":4,"vote_count":11},{"id":1439,"rating":3,"vote_count":30},{"id":1440,"rating":5,"vote_count":4},{"id":1441,"rating":4,"vote_count":110},{"id":1442,"rating":5,"vote_count":60},{"id":1443,"rating":5,"vote_count":55},{"id":1444,"rating":4,"vote_count":47},{"id":1445,"rating":4,"vote_count":53},{"id":1446,"rating":4,"vote_count":33},{"id":1447,"rating":3,"vote_count":18},{"id":1448,"rating":4,"vote_count":50},{"id":1449,"rating":5,"vote_count":6},{"id":1450,"rating":5,"vote_count":54},{"id":1451,"rating":4,"vote_count":22},{"id":1452,"rating":5,"vote_count":23},{"id":1453,"rating":5,"vote_count":20},{"id":1454,"rating":4,"vote_count":7},{"id":1455,"rating":5,"vote_count":11},{"id":1456,"rating":4,"vote_count":8},{"id":1457,"rating":4,"vote_count":6},{"id":1458,"rating":4,"vote_count":3},{"id":1459,"rating":5,"vote_count":40},{"id":1460,"rating":5,"vote_count":4},{"id":1461,"rating":5,"vote_count":308},{"id":1462,"rating":5,"vote_count":4},{"id":1521,"rating":5,"vote_count":47},{"id":1463,"rating":5,"vote_count":182},{"id":1464,"rating":4,"vote_count":16},{"id":1465,"rating":5,"vote_count":23},{"id":1466,"rating":5,"vote_count":8},{"id":1467,"rating":5,"vote_count":4},{"id":1468,"rating":5,"vote_count":117},{"id":1469,"rating":5,"vote_count":65},{"id":1470,"rating":4,"vote_count":3},{"id":1471,"rating":4,"vote_count":18},{"id":1472,"rating":5,"vote_count":31},{"id":1478,"rating":4,"vote_count":16},{"id":1473,"rating":5,"vote_count":24},{"id":1474,"rating":4,"vote_count":13},{"id":1475,"rating":4,"vote_count":46},{"id":1476,"rating":5,"vote_count":4},{"id":1477,"rating":5,"vote_count":81},{"id":1479,"rating":4,"vote_count":15},{"id":1480,"rating":4,"vote_count":11},{"id":1481,"rating":4,"vote_count":22},{"id":1482,"rating":5,"vote_count":48},{"id":1483,"rating":3,"vote_count":6},{"id":1484,"rating":5,"vote_count":31},{"id":1485,"rating":5,"vote_count":40},{"id":1486,"rating":4,"vote_count":10},{"id":1487,"rating":4,"vote_count":40},{"id":1488,"rating":4,"vote_count":131},{"id":1505,"rating":4,"vote_count":3},{"id":1489,"rating":4,"vote_count":3},{"id":1490,"rating":4,"vote_count":13},{"id":1491,"rating":5,"vote_count":23},{"id":1492,"rating":4,"vote_count":37},{"id":1493,"rating":4,"vote_count":8},{"id":1494,"rating":4,"vote_count":3},{"id":1495,"rating":4,"vote_count":11},{"id":1496,"rating":4,"vote_count":158},{"id":1497,"rating":4,"vote_count":11},{"id":1498,"rating":5,"vote_count":6},{"id":1499,"rating":5,"vote_count":6},{"id":1500,"rating":4,"vote_count":25},{"id":1501,"rating":5,"vote_count":14},{"id":1502,"rating":4,"vote_count":9},{"id":1503,"rating":5,"vote_count":160},{"id":1504,"rating":5,"vote_count":4},{"id":1510,"rating":5,"vote_count":11},{"id":1511,"rating":5,"vote_count":8},{"id":1512,"rating":5,"vote_count":1},{"id":1513,"rating":5,"vote_count":8},{"id":1514,"rating":5,"vote_count":5},{"id":1515,"rating":5,"vote_count":3},{"id":1535,"rating":5,"vote_count":1},{"id":1516,"rating":4,"vote_count":19},{"id":1517,"rating":4,"vote_count":63},{"id":1518,"rating":5,"vote_count":20},{"id":1519,"rating":5,"vote_count":12},{"id":1520,"rating":5,"vote_count":7},{"id":1522,"rating":4,"vote_count":63},{"id":1523,"rating":5,"vote_count":62},{"id":1524,"rating":4,"vote_count":6},{"id":1525,"rating":5,"vote_count":22},{"id":1526,"rating":5,"vote_count":14},{"id":1527,"rating":5,"vote_count":1},{"id":1528,"rating":5,"vote_count":140},{"id":1529,"rating":4,"vote_count":17},{"id":1530,"rating":5,"vote_count":37},{"id":1531,"rating":5,"vote_count":1},{"id":1532,"rating":5,"vote_count":27},{"id":1533,"rating":5,"vote_count":3},{"id":1534,"rating":5,"vote_count":3},{"id":1538,"rating":5,"vote_count":49},{"id":1539,"rating":5,"vote_count":12},{"id":1540,"rating":4,"vote_count":5},{"id":1541,"rating":4,"vote_count":336},{"id":1542,"rating":4,"vote_count":23},{"id":1543,"rating":5,"vote_count":1},{"id":1544,"rating":5,"vote_count":36},{"id":1545,"rating":5,"vote_count":7},{"id":1546,"rating":4,"vote_count":14},{"id":1547,"rating":5,"vote_count":16},{"id":1548,"rating":4,"vote_count":17},{"id":1549,"rating":5,"vote_count":16},{"id":1550,"rating":4,"vote_count":8},{"id":1551,"rating":5,"vote_count":12},{"id":1552,"rating":3,"vote_count":183},{"id":1553,"rating":4,"vote_count":12},{"id":1554,"rating":4,"vote_count":5},{"id":1555,"rating":5,"vote_count":45},{"id":1556,"rating":5,"vote_count":27},{"id":1557,"rating":4,"vote_count":29},{"id":1558,"rating":4,"vote_count":5},{"id":1559,"rating":4,"vote_count":3},{"id":1560,"rating":3,"vote_count":8},{"id":1561,"rating":4,"vote_count":76},{"id":1562,"rating":4,"vote_count":3},{"id":1563,"rating":5,"vote_count":18},{"id":1564,"rating":4,"vote_count":5},{"id":1565,"rating":5,"vote_count":19},{"id":1566,"rating":3,"vote_count":27},{"id":1567,"rating":4,"vote_count":23},{"id":1569,"rating":5,"vote_count":2},{"id":1570,"rating":5,"vote_count":13},{"id":1571,"rating":5,"vote_count":22},{"id":1572,"rating":5,"vote_count":37},{"id":1573,"rating":4,"vote_count":13},{"id":1574,"rating":4,"vote_count":12},{"id":1575,"rating":4,"vote_count":22},{"id":1576,"rating":5,"vote_count":35},{"id":1577,"rating":5,"vote_count":4},{"id":1578,"rating":5,"vote_count":7},{"id":1579,"rating":5,"vote_count":2},{"id":1580,"rating":4,"vote_count":3},{"id":1581,"rating":5,"vote_count":2},{"id":1582,"rating":4,"vote_count":29},{"id":1583,"rating":5,"vote_count":6},{"id":1584,"rating":5,"vote_count":84},{"id":1585,"rating":4,"vote_count":25},{"id":1586,"rating":4,"vote_count":27},{"id":1587,"rating":5,"vote_count":12},{"id":1588,"rating":3,"vote_count":3},{"id":1589,"rating":4,"vote_count":1},{"id":1590,"rating":4,"vote_count":6},{"id":1591,"rating":4,"vote_count":12},{"id":1592,"rating":5,"vote_count":10},{"id":1593,"rating":5,"vote_count":8},{"id":1594,"rating":4,"vote_count":4},{"id":1595,"rating":4,"vote_count":11},{"id":1596,"rating":4,"vote_count":31},{"id":1597,"rating":4,"vote_count":93},{"id":1598,"rating":3,"vote_count":6},{"id":1599,"rating":4,"vote_count":6},{"id":1600,"rating":4,"vote_count":36},{"id":1601,"rating":4,"vote_count":8},{"id":1602,"rating":4,"vote_count":33},{"id":1603,"rating":4,"vote_count":12},{"id":1604,"rating":5,"vote_count":1},{"id":1605,"rating":5,"vote_count":19},{"id":1606,"rating":3,"vote_count":3},{"id":1607,"rating":5,"vote_count":18},{"id":1608,"rating":4,"vote_count":12},{"id":1609,"rating":5,"vote_count":6},{"id":1610,"rating":5,"vote_count":10},{"id":1611,"rating":5,"vote_count":4},{"id":1612,"rating":5,"vote_count":8},{"id":1613,"rating":5,"vote_count":8},{"id":1614,"rating":3,"vote_count":11},{"id":1615,"rating":5,"vote_count":15},{"id":1616,"rating":5,"vote_count":24},{"id":1617,"rating":5,"vote_count":4},{"id":1618,"rating":5,"vote_count":7},{"id":1619,"rating":4,"vote_count":13},{"id":1620,"rating":5,"vote_count":7},{"id":1621,"rating":5,"vote_count":109},{"id":1622,"rating":5,"vote_count":19},{"id":1623,"rating":5,"vote_count":13},{"id":1624,"rating":5,"vote_count":8},{"id":1625,"rating":4,"vote_count":5},{"id":1626,"rating":4,"vote_count":9},{"id":1627,"rating":3,"vote_count":3},{"id":1628,"rating":5,"vote_count":8},{"id":1629,"rating":5,"vote_count":2},{"id":1630,"rating":5,"vote_count":2},{"id":1631,"rating":5,"vote_count":11},{"id":1632,"rating":5,"vote_count":4},{"id":1633,"rating":5,"vote_count":1},{"id":1634,"rating":5,"vote_count":13},{"id":1635,"rating":5,"vote_count":4},{"id":1636,"rating":5,"vote_count":4},{"id":1637,"rating":5,"vote_count":3},{"id":1638,"rating":5,"vote_count":2},{"id":1639,"rating":4,"vote_count":8},{"id":1640,"rating":5,"vote_count":1},{"id":1641,"rating":5,"vote_count":5},{"id":1643,"rating":5,"vote_count":2},{"id":1644,"rating":4,"vote_count":49},{"id":1645,"rating":4,"vote_count":3},{"id":1646,"rating":5,"vote_count":21},{"id":1647,"rating":4,"vote_count":10},{"id":1648,"rating":5,"vote_count":33},{"id":1649,"rating":5,"vote_count":66},{"id":1650,"rating":5,"vote_count":43},{"id":1651,"rating":4,"vote_count":45},{"id":1652,"rating":4,"vote_count":6},{"id":1653,"rating":3,"vote_count":4},{"id":1654,"rating":5,"vote_count":9},{"id":1656,"rating":5,"vote_count":14},{"id":1657,"rating":5,"vote_count":53},{"id":1658,"rating":5,"vote_count":18},{"id":1659,"rating":5,"vote_count":13},{"id":1660,"rating":4,"vote_count":3},{"id":1661,"rating":4,"vote_count":10},{"id":1662,"rating":4,"vote_count":8},{"id":1663,"rating":5,"vote_count":4},{"id":1664,"rating":4,"vote_count":4},{"id":1665,"rating":5,"vote_count":4},{"id":1666,"rating":5,"vote_count":16},{"id":1668,"rating":4,"vote_count":15},{"id":1669,"rating":5,"vote_count":6},{"id":1670,"rating":5,"vote_count":8},{"id":1671,"rating":5,"vote_count":6},{"id":1672,"rating":5,"vote_count":15},{"id":1673,"rating":5,"vote_count":7},{"id":1674,"rating":4,"vote_count":3},{"id":1675,"rating":5,"vote_count":2},{"id":1676,"rating":5,"vote_count":16},{"id":1677,"rating":5,"vote_count":22},{"id":1678,"rating":5,"vote_count":18},{"id":1679,"rating":5,"vote_count":7},{"id":1680,"rating":4,"vote_count":21},{"id":1681,"rating":5,"vote_count":13},{"id":1682,"rating":4,"vote_count":17},{"id":1683,"rating":4,"vote_count":19},{"id":1684,"rating":5,"vote_count":7}]